refractulator/__init__.py
refractulator/_version.py
refractulator/calculate.py
refractulator/data_generator.py
refractulator/visualization.py
refractulator-0.3.0.dist-info/LICENSE
refractulator-0.3.0.dist-info/METADATA
refractulator-0.3.0.dist-info/WHEEL
refractulator-0.3.0.dist-info/top_level.txt
refractulator-0.3.0.dist-info/RECORD
