Metadata-Version: 2.1
Name: refractulator
Version: 0.3.0
Summary: A package to calculate and visualize light interactions with water droplets.
Author-email: Scott Kilgore <kilgore.scott+github@gmail.com>
License: MIT
Project-URL: Homepage, https://github.com/ScottTpirate/refractulator
Project-URL: Documentation, https://github.com/ScottTpirate/refractulator#readme
License-File: LICENSE
Requires-Dist: numpy
Provides-Extra: visualization
Requires-Dist: plotly; extra == "visualization"
